abstract_clipit/__init__.py
abstract_clipit/imports.py
abstract_clipit/initFuncs.py
abstract_clipit/main.py
abstract_clipit/FileDropArea/__init__.py
abstract_clipit/FileDropArea/imports.py
abstract_clipit/FileDropArea/initFuncs.py
abstract_clipit/FileDropArea/main.py
abstract_clipit/FileDropArea/functions/__init__.py
abstract_clipit/FileDropArea/functions/directory_utils.py
abstract_clipit/FileDropArea/functions/python_utils.py
abstract_clipit/FileDropArea/functions/rebuild_utils.py
abstract_clipit/FileDropArea/functions/view_utils.py
abstract_clipit/FileSystemTree/__init__.py
abstract_clipit/FileSystemTree/imports.py
abstract_clipit/FileSystemTree/initFuncs.py
abstract_clipit/FileSystemTree/main.py
abstract_clipit/FileSystemTree/functions/__init__.py
abstract_clipit/FileSystemTree/functions/text_utils.py
abstract_clipit/JSBridge/JSBridge.py
abstract_clipit/JSBridge/__init__.py
abstract_clipit/clipitTab/__init__.py
abstract_clipit/clipitTab/getFnames.py
abstract_clipit/clipitTab/imports.py
abstract_clipit/clipitTab/initFuncs.py
abstract_clipit/clipitTab/main.py
abstract_clipit/clipitTab/functions/__init__.py
abstract_clipit/clipitTab/functions/drop_utils.py
abstract_clipit/imports/__init__.py
abstract_clipit/imports/imports.py
abstract_clipit/imports/qt_funcs.py
abstract_clipit/imports/utils.py
abstract_clipit/utils/__init__.py
abstract_clipit/utils/read_utils.py
abstract_clipit-0.0.1.58.dist-info/METADATA
abstract_clipit-0.0.1.58.dist-info/WHEEL
abstract_clipit-0.0.1.58.dist-info/top_level.txt
abstract_clipit-0.0.1.58.dist-info/RECORD
