Metadata-Version: 2.4
Name: abstract_clipit
Version: 0.0.1.58
Summary: Built using PyQt6, it provides a drag-and-drop interface, a file system browser, and a logging console, enabling users to easily copy file contents to the clipboard, parse Python files for functions and imports, and manage file extensions and directories dynamically.
Home-page: https://github.com/AbstractEndeavors/abstract_clipit
Author: putkoff
Author-email: partners@abstractendeavors.com
Classifier: Development Status :: 3 - Alpha
Classifier: Intended Audience :: Developers
Classifier: License :: OSI Approved :: MIT License
Classifier: Programming Language :: Python :: 3
Classifier: Programming Language :: Python :: 3.11
Requires-Python: >=3.6
Requires-Dist: PyQt6
Requires-Dist: abstract_gui
Requires-Dist: abstract_pandas
Requires-Dist: abstract_paths
Requires-Dist: abstract_utilities
Requires-Dist: pathlib
Requires-Dist: pdf2image
Requires-Dist: pytesseract
Dynamic: author
Dynamic: author-email
Dynamic: classifier
Dynamic: description
Dynamic: description-content-type
Dynamic: home-page
Dynamic: requires-dist
Dynamic: requires-python
Dynamic: summary
